{"items":[{"type":"part","part":{"partNumber":"A 230 540 58 07","name":"жгут электропроводки","positionCode":"10","description":"ОБОГРЕВ. ЗАДН. СТЕКЛО, МИНУС. ПРОВОД АНТЕНН. УСИЛИТЕЛЯ","imageUrl":"https://img.laximo.ru/MB201810/source/B/54/518000005_070621.gif?s=5255&k=9b9d3108b5b58a8a2e2eeb969346ef0d"},"usage":{"nodeId":"armtek-unit-40a418ffded6","positionLabel":"10","quantity":"001"},"node":{"id":"armtek-unit-40a418ffded6","name":"518 ЖГУТ ЭЛ.ПРОВОДКИ ЗАДН.СТЕКЛА С ОБОГРЕВОМ"}},{"type":"part","part":{"partNumber":"A 230 540 57 07","name":"жгут электропроводки","positionCode":"100","description":"ОБОГРЕВ ЗАДНЕГО СТЕКЛА, \"ПЛЮСОВОЙ\" ПРОВОД","imageUrl":"https://img.laximo.ru/MB201810/source/B/54/518000005_070621.gif?s=5255&k=9b9d3108b5b58a8a2e2eeb969346ef0d"},"usage":{"nodeId":"armtek-unit-40a418ffded6","positionLabel":"100","quantity":"001"},"node":{"id":"armtek-unit-40a418ffded6","name":"518 ЖГУТ ЭЛ.ПРОВОДКИ ЗАДН.СТЕКЛА С ОБОГРЕВОМ"}},{"type":"part","part":{"partNumber":"A 002 545 92 26","name":"корпус штекерной втулки","positionCode":"900","description":"ОБОГРЕВ ЗАДНЕГО СТЕКЛА 1-PIN PL6.3","imageUrl":"https://img.laximo.ru/MB201810/source/B/54/518000005_070621.gif?s=5255&k=9b9d3108b5b58a8a2e2eeb969346ef0d"},"usage":{"nodeId":"armtek-unit-40a418ffded6","positionLabel":"900","quantity":"001"},"node":{"id":"armtek-unit-40a418ffded6","name":"518 ЖГУТ ЭЛ.ПРОВОДКИ ЗАДН.СТЕКЛА С ОБОГРЕВОМ"}},{"type":"part","part":{"partNumber":"A 008 545 60 26","name":"муфта плоского штекера","positionCode":"901","description":"1.5-2.5 MM2 PL6.3","imageUrl":"https://img.laximo.ru/MB201810/source/B/54/518000005_070621.gif?s=5255&k=9b9d3108b5b58a8a2e2eeb969346ef0d"},"usage":{"nodeId":"armtek-unit-40a418ffded6","positionLabel":"901","quantity":"NB"},"node":{"id":"armtek-unit-40a418ffded6","name":"518 ЖГУТ ЭЛ.ПРОВОДКИ ЗАДН.СТЕКЛА С ОБОГРЕВОМ"}}]}
