{"items":[{"type":"part","part":{"partNumber":"A 230 470 22 01","name":"топливный бак","positionCode":"10","description":"Заменено на: A 230 470 44 01. ДЛЯ А/М БЕЗ КОДА 494 / 498 / 918 ЗАКАЗАТЬ ТАКЖЕ ВОРОНКУ","imageUrl":"https://img.laximo.ru/MB201810/source/B/47/015000178_080820.gif?s=5255&k=43bed45de63a079513900c6c3ef62058"},"usage":{"nodeId":"armtek-unit-6ff01627e45c","positionLabel":"10","quantity":"001"},"node":{"id":"armtek-unit-6ff01627e45c","name":"015 ТОПЛИВНЫЙ БАК С НАВЕСНЫМИ ЭЛЕМЕНТАМИ"}},{"type":"part","part":{"partNumber":"A 230 470 44 01","name":"топливный бак","positionCode":"10","description":"Заменено на: A 230 470 38 01. ДЛЯ А/М БЕЗ КОДА 494 / 498 / 918 ЗАКАЗАТЬ ТАКЖЕ ВОРОНКУ","imageUrl":"https://img.laximo.ru/MB201810/source/B/47/015000178_080820.gif?s=5255&k=43bed45de63a079513900c6c3ef62058"},"usage":{"nodeId":"armtek-unit-6ff01627e45c","positionLabel":"10","quantity":"001"},"node":{"id":"armtek-unit-6ff01627e45c","name":"015 ТОПЛИВНЫЙ БАК С НАВЕСНЫМИ ЭЛЕМЕНТАМИ"}},{"type":"part","part":{"partNumber":"A 230 470 38 01","name":"топливный бак","positionCode":"10","description":"","imageUrl":"https://img.laximo.ru/MB201810/source/B/47/015000178_080820.gif?s=5255&k=43bed45de63a079513900c6c3ef62058"},"usage":{"nodeId":"armtek-unit-6ff01627e45c","positionLabel":"10","quantity":"001"},"node":{"id":"armtek-unit-6ff01627e45c","name":"015 ТОПЛИВНЫЙ БАК С НАВЕСНЫМИ ЭЛЕМЕНТАМИ"}},{"type":"part","part":{"partNumber":"A 230 542 04 17","name":"ДАТЧИК","positionCode":"20","description":"НА БАКЕ, ВЕРХН. ЧАСТЬ","imageUrl":"https://img.laximo.ru/MB201810/source/B/47/015000178_080820.gif?s=5255&k=43bed45de63a079513900c6c3ef62058"},"usage":{"nodeId":"armtek-unit-6ff01627e45c","positionLabel":"20","quantity":"001"},"node":{"id":"armtek-unit-6ff01627e45c","name":"015 ТОПЛИВНЫЙ БАК С НАВЕСНЫМИ ЭЛЕМЕНТАМИ"}},{"type":"part","part":{"partNumber":"A 210 471 01 79","name":"УПЛОТНИТ. КОЛЬЦО","positionCode":"30","description":"ДАТЧИК НА ТОПЛ. БАЧКЕ","imageUrl":"https://img.laximo.ru/MB201810/source/B/47/015000178_080820.gif?s=5255&k=43bed45de63a079513900c6c3ef62058"},"usage":{"nodeId":"armtek-unit-6ff01627e45c","positionLabel":"30","quantity":"001"},"node":{"id":"armtek-unit-6ff01627e45c","name":"015 ТОПЛИВНЫЙ БАК С НАВЕСНЫМИ ЭЛЕМЕНТАМИ"}},{"type":"part","part":{"partNumber":"A 230 471 00 85","name":"пробка резьбовая","positionCode":"40","description":"КРЕПЛ. ТОПЛ. БАКА","imageUrl":"https://img.laximo.ru/MB201810/source/B/47/015000178_080820.gif?s=5255&k=43bed45de63a079513900c6c3ef62058"},"usage":{"nodeId":"armtek-unit-6ff01627e45c","positionLabel":"40","quantity":"004"},"node":{"id":"armtek-unit-6ff01627e45c","name":"015 ТОПЛИВНЫЙ БАК С НАВЕСНЫМИ ЭЛЕМЕНТАМИ"}},{"type":"part","part":{"partNumber":"A 230 470 03 05","name":"ЗАМОК ТОПЛ. БАКА","positionCode":"55","description":"НА ЗАПРАВОЧНОМ ПАТРУБКЕ. ПРИ МОНТАЖЕ ПОДОГНАТЬ ПО МЕСТУ","imageUrl":"https://img.laximo.ru/MB201810/source/B/47/015000178_080820.gif?s=5255&k=43bed45de63a079513900c6c3ef62058"},"usage":{"nodeId":"armtek-unit-6ff01627e45c","positionLabel":"55","quantity":"001"},"node":{"id":"armtek-unit-6ff01627e45c","name":"015 ТОПЛИВНЫЙ БАК С НАВЕСНЫМИ ЭЛЕМЕНТАМИ"}},{"type":"part","part":{"partNumber":"A 168 471 04 79","name":"УПЛОТНИТ. КОЛЬЦО","positionCode":"60","description":"ЗАМОК ТОПЛ. БАКА. Заменено на: A 000 476 00 00","imageUrl":"https://img.laximo.ru/MB201810/source/B/47/015000178_080820.gif?s=5255&k=43bed45de63a079513900c6c3ef62058"},"usage":{"nodeId":"armtek-unit-6ff01627e45c","positionLabel":"60","quantity":"001"},"node":{"id":"armtek-unit-6ff01627e45c","name":"015 ТОПЛИВНЫЙ БАК С НАВЕСНЫМИ ЭЛЕМЕНТАМИ"}},{"type":"part","part":{"partNumber":"A 000 476 00 00","name":"профильное уплотнение","positionCode":"60","description":"ЗАМОК ТОПЛ. БАКА","imageUrl":"https://img.laximo.ru/MB201810/source/B/47/015000178_080820.gif?s=5255&k=43bed45de63a079513900c6c3ef62058"},"usage":{"nodeId":"armtek-unit-6ff01627e45c","positionLabel":"60","quantity":"001"},"node":{"id":"armtek-unit-6ff01627e45c","name":"015 ТОПЛИВНЫЙ БАК С НАВЕСНЫМИ ЭЛЕМЕНТАМИ"}},{"type":"part","part":{"partNumber":"A 001 990 23 92","name":"распорная заклепка","positionCode":"65","description":"ЗАМОК ТОПЛ. БАКА 5.2 MM","imageUrl":"https://img.laximo.ru/MB201810/source/B/47/015000178_080820.gif?s=5255&k=43bed45de63a079513900c6c3ef62058"},"usage":{"nodeId":"armtek-unit-6ff01627e45c","positionLabel":"65","quantity":"001"},"node":{"id":"armtek-unit-6ff01627e45c","name":"015 ТОПЛИВНЫЙ БАК С НАВЕСНЫМИ ЭЛЕМЕНТАМИ"}},{"type":"part","part":{"partNumber":"A 116 470 01 29","name":"направляющая воронка","positionCode":"70","description":"ЗАЛИВН. ШТУЦЕР НА БОКОВОЙ СТЕНКЕ. Заменено на: A 169 470 00 29","imageUrl":"https://img.laximo.ru/MB201810/source/B/47/015000178_080820.gif?s=5255&k=43bed45de63a079513900c6c3ef62058"},"usage":{"nodeId":"armtek-unit-6ff01627e45c","positionLabel":"70","quantity":"001"},"node":{"id":"armtek-unit-6ff01627e45c","name":"015 ТОПЛИВНЫЙ БАК С НАВЕСНЫМИ ЭЛЕМЕНТАМИ"}},{"type":"part","part":{"partNumber":"A 169 470 00 29","name":"заливная горловина","positionCode":"70","description":"ЗАЛИВН. ШТУЦЕР НА БОКОВОЙ СТЕНКЕ","imageUrl":"https://img.laximo.ru/MB201810/source/B/47/015000178_080820.gif?s=5255&k=43bed45de63a079513900c6c3ef62058"},"usage":{"nodeId":"armtek-unit-6ff01627e45c","positionLabel":"70","quantity":"001"},"node":{"id":"armtek-unit-6ff01627e45c","name":"015 ТОПЛИВНЫЙ БАК С НАВЕСНЫМИ ЭЛЕМЕНТАМИ"}},{"type":"part","part":{"partNumber":"A 210 471 00 81","name":"манжета","positionCode":"80","description":"ОБРАТН. ПОТОК И ВЕНТИЛ. ТРУБОПРОВОД","imageUrl":"https://img.laximo.ru/MB201810/source/B/47/015000178_080820.gif?s=5255&k=43bed45de63a079513900c6c3ef62058"},"usage":{"nodeId":"armtek-unit-6ff01627e45c","positionLabel":"80","quantity":"001"},"node":{"id":"armtek-unit-6ff01627e45c","name":"015 ТОПЛИВНЫЙ БАК С НАВЕСНЫМИ ЭЛЕМЕНТАМИ"}},{"type":"part","part":{"partNumber":"A 124 471 04 81","name":"манжета","positionCode":"90","description":"НА ВСАСЫВ.ТРУБОПР.","imageUrl":"https://img.laximo.ru/MB201810/source/B/47/015000178_080820.gif?s=5255&k=43bed45de63a079513900c6c3ef62058"},"usage":{"nodeId":"armtek-unit-6ff01627e45c","positionLabel":"90","quantity":"001"},"node":{"id":"armtek-unit-6ff01627e45c","name":"015 ТОПЛИВНЫЙ БАК С НАВЕСНЫМИ ЭЛЕМЕНТАМИ"}},{"type":"part","part":{"partNumber":"A 210 470 01 06","name":"TS сетчатый топл. фильтр","positionCode":"100","description":"К-Т ДЕТАЛЕЙ","imageUrl":"https://img.laximo.ru/MB201810/source/B/47/015000178_080820.gif?s=5255&k=43bed45de63a079513900c6c3ef62058"},"usage":{"nodeId":"armtek-unit-6ff01627e45c","positionLabel":"100","quantity":"001"},"node":{"id":"armtek-unit-6ff01627e45c","name":"015 ТОПЛИВНЫЙ БАК С НАВЕСНЫМИ ЭЛЕМЕНТАМИ"}},{"type":"part","part":{"partNumber":"A 022 997 06 48","name":"уплотнительное кольцо","positionCode":"110","description":"ТОПЛ. СЕТЧ. ФИЛЬТР НА ТОПЛ. БАКЕ","imageUrl":"https://img.laximo.ru/MB201810/source/B/47/015000178_080820.gif?s=5255&k=43bed45de63a079513900c6c3ef62058"},"usage":{"nodeId":"armtek-unit-6ff01627e45c","positionLabel":"110","quantity":"001"},"node":{"id":"armtek-unit-6ff01627e45c","name":"015 ТОПЛИВНЫЙ БАК С НАВЕСНЫМИ ЭЛЕМЕНТАМИ"}},{"type":"part","part":{"partNumber":"A 230 997 01 86","name":"пробка","positionCode":"120","description":"НА ЗАМК.ЧАСТИ СНАРУЖИ СПРАВА","imageUrl":"https://img.laximo.ru/MB201810/source/B/47/015000178_080820.gif?s=5255&k=43bed45de63a079513900c6c3ef62058"},"usage":{"nodeId":"armtek-unit-6ff01627e45c","positionLabel":"120","quantity":"001"},"node":{"id":"armtek-unit-6ff01627e45c","name":"015 ТОПЛИВНЫЙ БАК С НАВЕСНЫМИ ЭЛЕМЕНТАМИ"}},{"type":"part","part":{"partNumber":"A 031 545 32 28","name":"корпус штекера","positionCode":"905","description":"ДАТЧИК ТОПЛИВА 2-PIN JPT2.8;B4","imageUrl":"https://img.laximo.ru/MB201810/source/B/47/015000178_080820.gif?s=5255&k=43bed45de63a079513900c6c3ef62058"},"usage":{"nodeId":"armtek-unit-6ff01627e45c","positionLabel":"905","quantity":"001"},"node":{"id":"armtek-unit-6ff01627e45c","name":"015 ТОПЛИВНЫЙ БАК С НАВЕСНЫМИ ЭЛЕМЕНТАМИ"}},{"type":"part","part":{"partNumber":"A 011 545 81 26","name":"контактная пружина","positionCode":"906","description":"ДАТЧИК ТОПЛИВА 0.5-1.0 MM2 JPT;B4","imageUrl":"https://img.laximo.ru/MB201810/source/B/47/015000178_080820.gif?s=5255&k=43bed45de63a079513900c6c3ef62058"},"usage":{"nodeId":"armtek-unit-6ff01627e45c","positionLabel":"906","quantity":"NB"},"node":{"id":"armtek-unit-6ff01627e45c","name":"015 ТОПЛИВНЫЙ БАК С НАВЕСНЫМИ ЭЛЕМЕНТАМИ"}}]}
